EXP/RIC.py
EXP/__init__.py
EXP/exp.py
EXP/exp_plot.py
EXP/explorer.py
EXP/linfit.py
EXP/tutorial_korean.py
EXP/uprint.py
EXP_jangddol-1.1.20.dist-info/LICENSE
EXP_jangddol-1.1.20.dist-info/METADATA
EXP_jangddol-1.1.20.dist-info/WHEEL
EXP_jangddol-1.1.20.dist-info/top_level.txt
EXP_jangddol-1.1.20.dist-info/RECORD
