Metadata-Version: 2.1
Name: EXP-jangddol
Version: 1.1.20
Summary: kawaii experiment data analysis tool
Home-page: https://github.com/jangddol/EXP_jangddol_pip.git
Author: jangddol
Author-email: j991005@korea.ac.kr
License: UNKNOWN
Platform: UNKNOWN
Classifier: Programming Language :: Python :: 3
Classifier: Operating System :: OS Independent
Requires-Dist: matplotlib (==3.5.0)
Requires-Dist: numpy (==1.21.0)
Requires-Dist: uncertainties (==3.1.6)
